pyfuelprices/__init__.py
pyfuelprices/_version.py
pyfuelprices/build_data.py
pyfuelprices/const.py
pyfuelprices/enum.py
pyfuelprices/fuel.py
pyfuelprices/fuel_locations.py
pyfuelprices/helpers.py
pyfuelprices/py.typed
pyfuelprices/schemas.py
pyfuelprices/sources/__init__.py
pyfuelprices/sources/mapping.py
pyfuelprices/sources/argentina/__init__.py
pyfuelprices/sources/argentina/const.py
pyfuelprices/sources/argentina/gobenergy.py
pyfuelprices/sources/australia/__init__.py
pyfuelprices/sources/australia/const.py
pyfuelprices/sources/australia/fuelsnoop.py
pyfuelprices/sources/australia/fuelwatch.py
pyfuelprices/sources/australia/petrolspy.py
pyfuelprices/sources/austria/__init__.py
pyfuelprices/sources/austria/const.py
pyfuelprices/sources/austria/spritpreisrechner.py
pyfuelprices/sources/belgium/__init__.py
pyfuelprices/sources/brazil/__init__.py
pyfuelprices/sources/brazil/const.py
pyfuelprices/sources/brazil/gaspass.py
pyfuelprices/sources/canada/__init__.py
pyfuelprices/sources/germany/__init__.py
pyfuelprices/sources/germany/const.py
pyfuelprices/sources/germany/tankerkoenig.py
pyfuelprices/sources/greece/__init__.py
pyfuelprices/sources/greece/const.py
pyfuelprices/sources/greece/fuelgr.py
pyfuelprices/sources/netherlands/__init__.py
pyfuelprices/sources/netherlands/const.py
pyfuelprices/sources/netherlands/directlease.py
pyfuelprices/sources/new_zealand/__init__.py
pyfuelprices/sources/new_zealand/const.py
pyfuelprices/sources/new_zealand/finelly.py
pyfuelprices/sources/romania/__init__.py
pyfuelprices/sources/romania/const.py
pyfuelprices/sources/romania/pecoonline.py
pyfuelprices/sources/slovenia/__init__.py
pyfuelprices/sources/slovenia/goriva.py
pyfuelprices/sources/switzerland/__init__.py
pyfuelprices/sources/switzerland/comparis.py
pyfuelprices/sources/uk/__init__.py
pyfuelprices/sources/uk/applegreenstores.py
pyfuelprices/sources/uk/ascona.py
pyfuelprices/sources/uk/asda.py
pyfuelprices/sources/uk/bpuk.py
pyfuelprices/sources/uk/const.py
pyfuelprices-2025.11.0.dist-info/licenses/LICENSE
pyfuelprices-2025.11.0.dist-info/METADATA
pyfuelprices-2025.11.0.dist-info/WHEEL
pyfuelprices-2025.11.0.dist-info/entry_points.txt
pyfuelprices-2025.11.0.dist-info/top_level.txt
pyfuelprices-2025.11.0.dist-info/RECORD
